Metadata-Version: 2.1
Name: weibo-poster
Version: 0.0.8
Summary: 对应 weibo-webhook 的提交器
Home-page: https://github.com/Drelf2018/weibo-poster
Author: Drelf2018
Author-email: drelf2018@outlook.com
License: MIT
Keywords: python,weibo,webhook
Platform: UNKNOWN
Classifier: Development Status :: 1 - Planning
Classifier: Intended Audience :: Developers
Classifier: Programming Language :: Python :: 3
Classifier: Operating System :: Unix
Classifier: Operating System :: MacOS :: MacOS X
Classifier: Operating System :: Microsoft :: Windows
Requires-Python: >=3.8
License-File: LICENSE
